Workbook
Name AgencyEmployeesDropdown: 'Drop-down'!$F$3
Name AgencyEmployeesDropdown: #REF!
Name AgencyEmployeesNumber: 'Drop-down'!$F$2
Name AgencyEmployeesNumber: #REF!
Name AgencyOwnershipDropdown: 'Drop-down'!#REF!
Name AgencyOwnershipDropdown: #REF!
Name AgencyOwnershipNumber: 'Drop-down'!#REF!
Name AgencyOwnershipNumber: #REF!
Name Billable: #REF!
Name Billable: #REF!
Name CountriesDropdown: 'Drop-down'!$D$3
Name CountriesDropdown: #REF!
Name CountriesNumber: 'Drop-down'!$D$2
Name CountriesNumber: #REF!
Name Currency: #REF!
Name Currency: #REF!
Name CurrencyDropdown: 'Drop-down'!$B$3
Name CurrencyDropdown: #REF!
Name CurrencyNumber: 'Drop-down'!$B$2
Name CurrencyNumber: #REF!
Name DeleteValue: #REF!
Name DeleteValue: #REF!
Name Dept1: #REF!
Name Dept1: #REF!
Name Dept2: #REF!
Name Dept2: #REF!
Name Dept3: #REF!
Name Dept3: #REF!
Name Dept4: #REF!
Name Dept4: #REF!
Name Dept5: #REF!
Name Dept5: #REF!
Name Dept6: #REF!
Name Dept6: #REF!
Name Dept7: #REF!
Name Dept7: #REF!
Name Dept8: #REF!
Name Dept8: #REF!
Name Margin: #REF!
Name Margin: #REF!
Name RangeAddRows: #REF!,#REF!,#REF!,#REF!,#REF!,#REF!,#REF!,#REF!
Name RangeAddRows: #REF!,#REF!,#REF!,#REF!,#REF!,#REF!,#REF!,#REF!
Name RangeAgencyEmployees: OFFSET(AgencyEmployeesDropdown,1,0):OFFSET(AgencyEmployeesDropdown,AgencyEmployeesNumber,0)
Name RangeAgencyEmployees: OFFSET('Drop-down'!AgencyEmployeesDropdown,1,0):OFFSET('Drop-down'!AgencyEmployeesDropdown,'Drop-down'!AgencyEmployeesNumber,0)
Name RangeAgencyEmployees: OFFSET(AgencyEmployeesDropdown,1,0):OFFSET(AgencyEmployeesDropdown,AgencyEmployeesNumber,0)
Name RangeAgencyOwnership: OFFSET(AgencyOwnershipDropdown,1,0):OFFSET(AgencyOwnershipDropdown,AgencyOwnershipNumber,0)
Name RangeAgencyOwnership: OFFSET('Drop-down'!AgencyOwnershipDropdown,1,0):OFFSET('Drop-down'!AgencyOwnershipDropdown,'Drop-down'!AgencyOwnershipNumber,0)
Name RangeAgencyOwnership: OFFSET(AgencyOwnershipDropdown,1,0):OFFSET(AgencyOwnershipDropdown,AgencyOwnershipNumber,0)
Name RangeCountries: OFFSET(CountriesDropdown,1,0):OFFSET(CountriesDropdown,CountriesNumber,0)
Name RangeCountries: OFFSET('Drop-down'!CountriesDropdown,1,0):OFFSET('Drop-down'!CountriesDropdown,'Drop-down'!CountriesNumber,0)
Name RangeCountries: OFFSET(CountriesDropdown,1,0):OFFSET(CountriesDropdown,CountriesNumber,0)
Name RangeCurrencies: OFFSET(CurrencyDropdown,1,0):OFFSET(CurrencyDropdown,CurrencyNumber,0)
Name RangeCurrencies: OFFSET('Drop-down'!CurrencyDropdown,1,0):OFFSET('Drop-down'!CurrencyDropdown,'Drop-down'!CurrencyNumber,0)
Name RangeCurrencies: OFFSET(CurrencyDropdown,1,0):OFFSET(CurrencyDropdown,CurrencyNumber,0)
Name RangeDeleteRow: #REF!
Name RangeDeleteRow: #REF!
Name RangeTableText: #REF!

Sheet Introduction
C3: #VALUE!
C5: RFI - Request for Information
C7: Agency:
C10: The purpose of this RFI is to collect all the preliminary information from the agency.
C11: It is important to read and understand the RFI document before filling out the template.
C12: NOTE: Some infomation, if not completed, will be parameterized to industry benchmarks
C14: Confidential © | VA Consulting All Rights Reserved
C15: Mobile: +39 3355718508 | Email: stefano.arbitrio@va-consulting.com
C16: Mobile: +39 3455339480 | Email: matteo.siffredi@va-consulting.com
C17: HQ Milan - Piazza Velasca, 6
C18: HQ Rome - Via Pistoia, 11
C20: #VALUE! | E20: Latest update | F20: =TODAY() -> 46000

Sheet RFI
B2: #VALUE!
M4: RFI - Request for Information
B6: GENERAL INFORMATION
C9: Registered Business Name | O9: D-U-N-S® number | AA9: VAT Registration Number
C12: Legal form: | O12: Company registration number: | AA12: Year Enstablished:
B16: ORGANIZATION & STRUCTURE
C19: # of Employees | O19: Company Level | AA19: Parent Company Name
C22: Category | O22: Agency Currency | U22: Euro - EUR | AA22: Trade Organizations
B26: REGISTERED OFFICE ADDRESS
C29: Country Coverage | O29: Address | AA29: Postcode
C31: City | O31: Country
B34: CONTACT DETAILS
I37: CEO | O37: General Manager | U37: Business Director | AA37: Executive Producer
C38: Name
C39: Surname
C40: Linkedin
C41: Telephone
C42: Mobile
C43: Email
B46: SOCIAL MEDIA
C49: Official Website | O49: X (Twitter) | AA49: Facebook
C51: Linkedin | O51: Instagram | AA51: Tiktok
C53: Pinterest | O53: Tumblr | AA53: Snapchat
C55: Reddit
B58: TURNOVER & CLIENTS | K58: Please provide revenue in euros using the full numeric format (e.g., 12.345.678,00 €).
K61: LOCAL | O61: GLOBAL | S61: NAM | W61: EUROPE | AA61: LATAM | AE61: AFRICA | AI61: APAC
C62: 2024 | E62: Annual Revenue
E63: EBITA
C64: 2023 | E64: Annual Revenue
E65: EBITA
C66: 2022 | E66: Annual Revenue
E67: EBITA
C68: 2021 | E68: Annual Revenue
E69: EBITA
C70: 2020 | E70: Annual Revenue
E71: EBITA
C74: Main Clients | H74: Industry | M74: Principal Activities | S74: Year | V74: ="Turnover in"&" "&RIGHT($U$22,3) -> Turnover in EUR | AB74: Client incidence in % | AI74: Exclusivity
AI75: FALSE
AI76: FALSE
AI77: FALSE
AI78: FALSE
AI79: FALSE
AI80: FALSE
C82: Note: Please complete the section below only upon receipt of this Request for Information (RFI) during a pitch process.
AG84: Yes | AI84: No
C85: Please specify whether your company is currently working or has previously worked with the CLIENT. | AG85: FALSE | AI85: FALSE
C87: If Yes, please fill the form below:
C89: Client Division | M89: Principal Activities | S89: Year | V89: ="Turnover in"&" "&RIGHT($U$22,3) -> Turnover in EUR | AB89: Client incidence in %
C97: Duration of Engagement with the Client
B100: KNOWLEDGE & COMPETENCIES
C103: Please delineate your areas of expertise in communication, with percentage allocations for each. (in the past 3 years).
C104: Communication Areas
C105: Automotive & Mobility | N105: FALSE | P105: Energy | Z105: FALSE | AB105: Lifestyle | AL105: FALSE
C106: Beauty & Personal Care | N106: FALSE | P106: Entertainment & Media | Z106: FALSE | AB106: Mobility & Transportation | AL106: FALSE
C107: Beverage | N107: FALSE | P107: Fashion & Luxury | Z107: FALSE | AB107: Pet Care | AL107: FALSE
C108: Consumer Goods | N108: FALSE | P108: Food & Beverage | Z108: FALSE | AB108: Sport & Outdoor | AL108: FALSE
C109: Corporate & B2B | N109: FALSE | P109: Healthcare & Pharma | Z109: FALSE | AB109: Tobacco | AL109: FALSE
C110: Electronics & Technology | N110: FALSE | P110: Home & Living | Z110: FALSE | AB110: Travel, Tourism & Hospitality | AL110: FALSE
C112: Total | F112: =L105+L106+L107+L108+L109+L110+X105+X106+X107+X108+X109+X110+AJ105+AJ106+AJ107+AJ108+AJ109+AJ110 -> 0
C114: Services
C115: Pre-Production
C116: Director Scouting | N116: FALSE | P116: Location scouting | Z116: FALSE | AB116: Booklet creation | AL116: FALSE
C117: Casting Scounting | N117: FALSE
C118: Production
C119: Rental of technical equipment | N119: FALSE | P119: Crew | Z119: FALSE | AB119: Logistics for the client | AL119: FALSE
C120: Purchase of HDDs for footage | N120: FALSE | P120: Delivery to post-production | Z120: FALSE | AB120: Logistics for the Agency | AL120: FALSE
C121: Post-Production
C122: Coordination of post-production | N122: FALSE | O122: Possibility of delivering to broadcasters | Z122: FALSE
B125: POST PRODUCTION
C128: Please; indicate whether you have an in-house post-production department. If so, which services does it cover (editing, color grading, VFX, sound design, etc.)? | AJ128: Yes | AL128: No
AJ129: FALSE | AL129: FALSE
C131: If outsourced, which companies do you usually collaborate with?
C133: Name | L133: Location | U133: Audio | AD133: Video
U134: FALSE | AD134: FALSE
U135: FALSE | AD135: FALSE
U136: FALSE | AD136: FALSE
U137: FALSE | AD137: FALSE
U138: FALSE | AD138: FALSE
U139: FALSE | AD139: FALSE
U140: FALSE | AD140: FALSE
U141: FALSE | AD141: FALSE
U142: FALSE | AD142: FALSE
U143: FALSE | AD143: FALSE
B146: ABOUT
C149: About
C152: Philosophy & Competitive Advantages
C155: Network Description
C158: Local Rapresentation
B162: GOVERNANCE & SOW
C165: Kindly detail the control and quality assurance systems established within your designated Creative Network for the purpose of monitoring and managing performance and Service Level Agreements (SLAs).
C168: Please outline the protocols in place for managing client data within your selected Creative Network, particularly if these differ from those of the Holding Group. Furthermore, please specify if your Creative Network utilises its own Data Management Platform (DMP).
C170: With regard to global brand governance, please clarify the distinction between global and local strategies. Describe the processes, including tools, systems, and the level of autonomy within a structured framework, employed to manage global governance and local adaptation.
C174: Please include any additional information that you deem pertinent.
B178: ACTIVITIES
Z180: Yes | AB180: No
C181: Please indicate if your company subcontract activities or some phase of services | Z181: FALSE | AB181: FALSE
C183: If Yes, please fill the form below:
C185: Activities outsourced | O185: detailed description | AA185: % Contractual value
B193: PEOPLE
C196: Note: Please complete the Annual Salary column only upon receipt of this Request for Information (RFI) during a pitch process.
...

Sheet Settings
A1: Mobile: +39 3890482133 | Email: andrea.cenciarelli@va-consulting.com | C1: 0.05
A2: Mobile: +39 3455339480 | Email: matteo.siffredi@va-consulting.com | C2: 0.1
A3: Mobile: +39 3334755586 | Email: martina.vietri@va-consulting.com | C3: 0.15
A4: Mobile: +39 3356368868 | Email: flavia.arbitrio@va-consulting.com | C4: 0.2
C5: 0.25
C6: 0.3
C7: 0.35
C8: 0.4
C9: 0.45
C10: 0.5
C11: 0.55
C12: 0.6
C13: 0.65
C14: 0.7
C15: 0.75
C16: 0.8
... C20: 1

Sheet Drop-down
B2: =COUNTA(B4:B197) -> 163 | D2: =COUNTA(D4:D197) -> 194 | F2: =COUNTA(F4:F197) -> 6
B3: Currency of rates | D3: Country | F3: Number of agency employees
B4: Australian Dollar - AUD | D4: Afghanistan | F4: 1 to 10
B5: British Pound - GBP | D5: Albania | F5: 11 to 50
B6: Euro - EUR | D6: Algeria | F6: 51 to 100
B7: Japanese Yen - JPY | D7: Andorra | F7: 101 to 250
B8: Swiss Franc - CHF | D8: Angola | F8: 251 to 400
B9: US Dollar - USD | D9: Antigua and Barbuda | F9: 401 +
B10: Afghanistan Afghani - AFN | D10: Argentina
B11: Albanian Lek - ALL | D11: Armenia
B12: Algerian Dinar - DZD | D12: Australia
B13: Angolan Kwanza - AOA | D13: Austria
B14: Argentine Peso - ARS | D14: Azerbaijan
B15: Armenian Dram - AMD | D15: Bahamas
B16: Aruban Florin - AWG | D16: Bahrain
B17: Australian Dollar - AUD | D17: Bangladesh
B18: Azerbaijan New Manat - AZN | D18: Barbados
B19: Bahamian Dollar - BSD | D19: Belarus
B20: Bahraini Dinar - BHD | D20: Belgium
B21: Bangladeshi Taka - BDT | D21: Belize
... B166: Zimbabwe Dollar - ZWD | D166: Spain
D167: Sri Lanka
D168: Sudan
D169: Suriname
D170: Swaziland
D171: Sweden
D172: Switzerland
D173: Syria
D174: Tajikistan
D175: Tanzania
D176: Thailand
D177: Togo
D178: Tonga
... D197: Zimbabwe

Sheet Dati Dashboard
A1: Agency | B1: Year enstablished: | C1: Parent Company Name | D1: # of Employees | E1: AR G 2024 | F1: AR G 2023 | G1: AR G 2022 | H1: AR G 2021 | I1: AR G 2020 | J1: EBIDTA G 2024 | K1: EBIDTA G 2023 | L1: EBIDTA G 2022 | M1: EBIDTA G 2021 | N1: EBIDTA G 2020 | O1: AR L 2024 | P1: AR L 2023 | Q1: AR L 2022 | R1: AR L 2021 | S1: AR L 2020 | T1: EBIDTA L 2024 | U1: EBIDTA L 2023 | V1: EBIDTA L 2022 | W1: EBIDTA L 2021 | X1: EBIDTA L 2020 | Y1: Automotive & Mobility | Z1: Beauty & Personal Care | AA1: Beverage | AB1: Consumer Goods | AC1: Corporate & B2B | AD1: Electronics & Technology | AE1: Energy | AF1: Entertainment & Media | AG1: Fashion & Luxury | AH1: Food & Beverage | AI1: Healthcare & Pharma | AJ1: Home & Living | AK1: Lifestyle | AL1: Mobility & Transportation | AM1: Pet Care | AN1: Sport & Outdoor | AO1: Tobacco | AP1: Travel, Tourism & Hospitality | AQ1: Services | AR1: Strategic & Consulting | AS1: Creative & Content | AT1: Audio / Visual Production | AU1: PR & Events | AV1: Above the Line | AW1: Below the Line | AX1: Digital Marketing | AY1: Social media & Influencer Marketing | AZ1: Technology & Digital | BA1: Analytics & Reporting | BB1: Email & Content Marketing | BC1: Trade Marketing | BD1: Retail | BE1: Media
A2: =RFI!I13 -> 0 | B2: =RFI!AG16 -> 0 | C2: =RFI!AG19 -> 0 | D2: =RFI!AG22 -> 0 | E2: =RFI!I63 -> 0 | F2: =RFI!J63 -> 0 | G2: =RFI!K63 -> 0 | H2: =RFI!L63 -> 0 | I2: =RFI!M63 -> 0 | J2: =RFI!N63 -> 0 | K2: =RFI!O63 -> 0 | L2: =RFI!P63 -> 0 | ... X2: =RFI!AB63 -> 0 | Y2: =RFI!L105 -> 0 | Z2: =RFI!L106 -> 0 | AA2: =RFI!L107 -> 0 | AB2: =RFI!L108 -> 0 | AC2: =RFI!L109 -> 0 | AD2: =RFI!L110 -> 0 | AE2: =RFI!X105 -> 0 | AF2: =RFI!X106 -> 0 | AG2: =RFI!X107 -> 0 | AH2: =RFI!X108 -> 0 | AI2: =RFI!X109 -> 0 | AJ2: =RFI!X110 -> 0 | AK2: =RFI!AJ105 -> 0 | AL2: =RFI!AJ106 -> 0 | AM2: =RFI!AJ107 -> 0 | AN2: =RFI!AJ108 -> 0 | AO2: =RFI!AJ109 -> 0 | AP2: =RFI!AJ110 -> 0 | AQ2: =AS6 -> 0 | AR2: =AX5 -> 0 | AS2: =AX6 -> 0 | AT2: =AX7 -> 0 | AU2: =AX8 -> 0 | AV2: =AX9 -> 0 | AW2: =AX10 -> 0 | AX2: =AX11 -> 0 | AY2: =AX12 -> 0 | AZ2: =AX13 -> 0 | BA2: =AX14 -> 0 | BB2: =AX15 -> 0 | BC2: =AX16 -> 0 | BD2: =AX17 -> 0 | BE2: =AX18 -> 0
AS5: =COUNTIF(AR6:AR87,"true") -> 0 | AU5: Strategic & Consulting | AV5: =COUNTIF(AR6:AR13,"true") -> 0 | AW5: 8 | AX5: =AV5/AW5 -> 0
AQ6: Strategic Planning | AR6: =RFI!N116 -> FALSE | AS6: =AS5/86 -> 0 | AU6: Creative & Content | AV6: =COUNTIF(AR14:AR22,"true") -> 0 | AW6: 9 | AX6: =AV6/AW6 -> 0
AQ7: Brand Audit | AR7: =RFI!#REF! -> #REF! | AU7: Audio / Visual Production | AV7: =COUNTIF(AR23:AR25,"true") -> 0 | AW7: 3 | AX7: =AV7/AW7 -> 0
AQ8: Brand Identity Development | AR8: =RFI!#REF! -> #REF! | AU8: PR & Events | AV8: =COUNTIF(AR26:AR32,"true") -> 0 | AW8: 7 | AX8: =AV8/AW8 -> 0
AQ9: Positioning Strategy Development | AR9: =RFI!Z116 -> FALSE | AU9: Above the Line | AV9: =COUNTIF(AR33:AR38,"true") -> 0 | AW9: 6 | AX9: =AV9/AW9 -> 0
AQ10: Reputation Management | AR10: =RFI!#REF! -> #REF! | AU10: Below the Line | AV10: =COUNTIF(AR39:AR43,"true") -> 0 | AW10: 5 | AX10: =AV10/AW10 -> 0
AQ11: Crisis Management | AR11: =RFI!#REF! -> #REF! | AU11: Digital Marketing | AV11: =COUNTIF(AR49:AR54,"true") -> 0 | AW11: 6 | AX11: =AV11/AW11 -> 0
AQ12: Marketing Research | AR12: =RFI!AL116 -> FALSE | AU12: Social media & Influencer Marketing | AV12: =COUNTIF(AR50:AR56,"true") -> 0 | AW12: 7 | AX12: =AV12/AW12 -> 0
AQ13: Consumer Insight | AR13: =RFI!#REF! -> #REF! | AU13: Technology & Digital | AV13: =COUNTIF(AR57:AR63,"true") -> 0 | AW13: 7 | AX13: =AV13/AW13 -> 0
AQ14: Campaign Creation | AR14: =RFI!N119 -> FALSE | AU14: Analytics & Reporting | AV14: =COUNTIF(AR64:AR67,"true") -> 0 | AW14: 4 | AX14: =AV14/AW14 -> 0
AQ15: Creative Concept Development | AR15: =RFI!N120 -> FALSE | AU15: Email & Content Marketing | AV15: =COUNTIF(AR68:AR72,"true") -> 0 | AW15: 5 | AX15: =AV15/AW15 -> 0
AQ16: Creative Production | AR16: =RFI!#REF! -> #REF! | AU16: Trade Marketing | AV16: =COUNTIF(AR73:AR77,"true") -> 0 | AW16: 5 | AX16: =AV16/AW16 -> 0
AQ17: Content Creattion Copywriting | AR17: =RFI!Z119 -> FALSE | AU17: Retail | AV17: =COUNTIF(AR78:AR82,"true") -> 0 | AW17: 5 | AX17: =AV17/AW17 -> 0
AQ18: Graphic Design | AR18: =RFI!Z120 -> FALSE | AU18: Media | AV18: =COUNTIF(AR83:AR87,"true") -> 0 | AW18: 5 | AX18: =AV18/AW18 -> 0
AQ19: Point of Sale Materials | AR19: =RFI!#REF! -> #REF!
AQ20: Photography | AR20: =RFI!AL119 -> FALSE
AQ21: Illustration | AR21: =RFI!AL120 -> FALSE
AQ22: Motion Graphics & Animation | AR22: =RFI!#REF! -> #REF!
AQ23: Video Production | AR23: =RFI!N122 -> FALSE
AQ24: Audio Production | AR24: =RFI!Z122 -> FALSE
AQ25: Post Production & Editing | AR25: =RFI!AL122 -> 0
AQ26: Media Relations | AR26: =RFI!#REF! -> #REF!
AQ27: Public Relations Strategy | AR27: =RFI!#REF! -> #REF!
AQ28: Influencer Relations | AR28: =RFI!#REF! -> #REF!
AQ29: Press Releases & Press Kits | AR29: =RFI!#REF! -> #REF!
AQ30: Event Organization & Mng | AR30: =RFI!#REF! -> #REF!
AQ31: Sponsorshi Management | AR31: =RFI!#REF! -> #REF!
AQ32: Experiental Marketing | AR32: =RFI!#REF! -> #REF!
AQ33: Media Management | AR33: =RFI!#REF! -> #REF!
AQ34: Media Planning | AR34: =RFI!#REF! -> #REF!
AQ35: Media Buying | AR35: =RFI!#REF! -> #REF!
AQ36: Media Agencies Coordination | AR36: =RFI!#REF! -> #REF!
AQ37: Broadcast Advertising | AR37: =RFI!#REF! -> #REF!
... AQ87: Media Monitoring | AR87: =RFI!#REF! -> #REF!
